cyanotype/__init__.py
cyanotype-0.0.1.dist-info/METADATA
cyanotype-0.0.1.dist-info/WHEEL
cyanotype-0.0.1.dist-info/top_level.txt
cyanotype-0.0.1.dist-info/RECORD
