Metadata-Version: 2.1
Name: cyanotype
Version: 0.0.1
Summary: Cyanotype
Author-email: Richard Kent <qpotizo@gmail.com>
Project-URL: Homepage, https://github.com/sparverius/cyanotype
Project-URL: Bug Tracker, https://github.com/sparverius/cyanotype/issues
